{
    "network-performance-jupyter-master/experiments.py": {
        "run_experiment": {
            "name": "run_experiment",
            "location": 34,
            "return": [
                "None"
            ],
            "arguments": {
                "hyperparameters_file_name": [
                    "str",
                    "Optional[str]"
                ],
                "experiment_name": [
                    "str"
                ]
            }
        }
    },
    "network-performance-jupyter-master/generate_trace.py": {
        "generate_trace_file": {
            "name": "generate_trace_file",
            "location": 4,
            "return": [
                "None"
            ],
            "arguments": {
                "trace_file_path": [
                    "str"
                ],
                "bandwidth": [
                    "float"
                ]
            }
        }
    },
    "network-performance-jupyter-master/run_receiver.py": {
        "main": {
            "name": "main",
            "location": 7,
            "return": [
                "None"
            ],
            "arguments": {}
        }
    },
    "network-performance-jupyter-master/src/helpers.py": {
        "generate_mahimahi_command": {
            "name": "generate_mahimahi_command",
            "location": 21,
            "return": [
                "str"
            ],
            "arguments": {
                "mahimahi_settings": [
                    "dict"
                ]
            }
        },
        "get_open_udp_port": {
            "name": "get_open_udp_port",
            "location": 55,
            "return": [
                "str",
                "List[List[int]]",
                "list",
                "List[str]"
            ],
            "arguments": {}
        },
        "print_performance": {
            "name": "print_performance",
            "location": 66,
            "return": [
                "None"
            ],
            "arguments": {
                "senders": [
                    "List[src.senders.Sender]"
                ],
                "num_seconds": [
                    "int"
                ],
                "episode_num": [
                    "int"
                ],
                "write_to_disk": [
                    "bool"
                ],
                "output_dir": [
                    "str"
                ],
                "experiment_dir": [
                    "str"
                ]
            }
        },
        "run_with_mahi_settings": {
            "name": "run_with_mahi_settings",
            "location": 130,
            "return": [
                "None"
            ],
            "arguments": {
                "mahimahi_settings": [
                    "dict"
                ],
                "seconds_to_run": [
                    "int"
                ],
                "senders": [
                    "list"
                ],
                "should_print_performance": [
                    "bool"
                ],
                "episode_num": [
                    "int"
                ],
                "write_to_disk": [
                    "bool"
                ],
                "output_dir": [
                    "str"
                ],
                "experiment_dir": [
                    "str"
                ]
            }
        }
    },
    "network-performance-jupyter-master/src/ml_helpers.py": {
        "optimize_model": {
            "name": "optimize_model",
            "location": 11,
            "return": [
                "None",
                "Dict[str, Any]",
                "bytes",
                "Optional[Dict[str, Any]]",
                "dict"
            ],
            "arguments": {
                "policy_net": [
                    "float",
                    "bool"
                ],
                "target_net": [
                    "bool",
                    "int",
                    "dict[, ]",
                    "Optional[dict]",
                    "None",
                    "Tuple[str]",
                    "tuple[str]"
                ],
                "device": [
                    "bool"
                ],
                "optimizer": [
                    "float",
                    "bool"
                ],
                "transitions": [
                    "int",
                    "Tuple[int, int]",
                    "float",
                    "Tuple[float, float, float]",
                    "bool"
                ],
                "batch_size": [
                    "float",
                    "int",
                    "Optional[set]",
                    "Optional[int]",
                    "Tuple[float, float, float]",
                    "List[float]",
                    "bool"
                ],
                "reward_decay": [
                    "float",
                    "int"
                ]
            }
        },
        "LSTM_DQN.__init__": {
            "name": "__init__",
            "location": 48,
            "return": [
                "None"
            ],
            "arguments": {
                "self": [],
                "config": [
                    "str",
                    "dict"
                ],
                "device": [
                    "List[List[float]]",
                    "list[list[float]]",
                    "Dict[str, Any]",
                    "dict[str, typing.Any]"
                ],
                "use_cuda": [
                    "bool",
                    "dict",
                    "Dict[str, Any]",
                    "str",
                    "Dict[str, str]"
                ]
            }
        },
        "LSTM_DQN.forward": {
            "name": "forward",
            "location": 76,
            "return": [
                "str",
                "bool"
            ],
            "arguments": {
                "self": [],
                "x": [
                    "int"
                ]
            }
        }
    },
    "network-performance-jupyter-master/src/ml_strategy.py": {
        "ReinforcementStrategy.__init__": {
            "name": "__init__",
            "location": 16,
            "return": [
                "None"
            ],
            "arguments": {
                "self": [],
                "policy_net": [
                    "src.ml_helpers.LSTM_DQN"
                ],
                "target_net": [
                    "src.ml_helpers.LSTM_DQN"
                ],
                "device": [
                    "int",
                    "float"
                ],
                "optimizer": [
                    "int",
                    "float"
                ],
                "hyperparameters": [
                    "dict"
                ],
                "episode_num": [
                    "int"
                ],
                "transitions": [
                    "List[dict]"
                ]
            }
        },
        "ReinforcementStrategy.select_next_action": {
            "name": "select_next_action",
            "location": 47,
            "return": [],
            "arguments": {
                "self": [],
                "state": [
                    "int",
                    "dict[str, typing.Any]",
                    "dict[, ]"
                ]
            }
        },
        "ReinforcementStrategy.window_is_open": {
            "name": "window_is_open",
            "location": 58,
            "return": [
                "bool"
            ],
            "arguments": {
                "self": []
            }
        },
        "ReinforcementStrategy.next_packet_to_send": {
            "name": "next_packet_to_send",
            "location": 65,
            "return": [
                "Optional[str]"
            ],
            "arguments": {
                "self": []
            }
        },
        "ReinforcementStrategy.handle_packet_loss": {
            "name": "handle_packet_loss",
            "location": 109,
            "return": [
                "None"
            ],
            "arguments": {
                "self": [],
                "seq_num": [
                    "int"
                ],
                "segment": [
                    "dict"
                ]
            }
        },
        "ReinforcementStrategy.compute_w_cubic": {
            "name": "compute_w_cubic",
            "location": 124,
            "return": [
                "int"
            ],
            "arguments": {
                "self": [],
                "t": [
                    "float"
                ]
            }
        },
        "ReinforcementStrategy.process_ack": {
            "name": "process_ack",
            "location": 128,
            "return": [
                "None"
            ],
            "arguments": {
                "self": [],
                "serialized_ack": [
                    "str"
                ]
            }
        },
        "ReinforcementStrategy.state_to_tensor": {
            "name": "state_to_tensor",
            "location": 202,
            "return": [],
            "arguments": {
                "self": [],
                "state": [
                    "list"
                ]
            }
        },
        "ReinforcementStrategy.take_action": {
            "name": "take_action",
            "location": 208,
            "return": [
                "None"
            ],
            "arguments": {
                "self": [],
                "action": [
                    "int"
                ]
            }
        },
        "ReinforcementStrategy.update_q_function": {
            "name": "update_q_function",
            "location": 226,
            "return": [
                "None"
            ],
            "arguments": {
                "self": [],
                "seq_num": [
                    "int"
                ],
                "rtt": [
                    "float"
                ],
                "dropped_packet": [
                    "bool"
                ]
            }
        },
        "ReinforcementStrategy.compute_state": {
            "name": "compute_state",
            "location": 259,
            "return": [
                "List[dict]"
            ],
            "arguments": {
                "self": [],
                "begin": [
                    "int"
                ],
                "end": [
                    "int"
                ]
            }
        },
        "ReinforcementStrategy.compute_reward": {
            "name": "compute_reward",
            "location": 264,
            "return": [],
            "arguments": {
                "self": [],
                "rtt": [
                    "float"
                ],
                "action": [
                    "int"
                ],
                "dropped_packet": [
                    "bool"
                ]
            }
        }
    },
    "network-performance-jupyter-master/src/receiver.py": {
        "Peer.__init__": {
            "name": "__init__",
            "location": 20,
            "return": [
                "None"
            ],
            "arguments": {
                "self": [],
                "port": [
                    "int"
                ],
                "window_size": [
                    "int"
                ]
            }
        },
        "Peer.window_has_no_missing_segments": {
            "name": "window_has_no_missing_segments",
            "location": 29,
            "return": [
                "bool"
            ],
            "arguments": {
                "self": []
            }
        },
        "Peer.update_high_water_mark": {
            "name": "update_high_water_mark",
            "location": 34,
            "return": [
                "None"
            ],
            "arguments": {
                "self": []
            }
        },
        "Peer.process_window": {
            "name": "process_window",
            "location": 45,
            "return": [
                "None"
            ],
            "arguments": {
                "self": []
            }
        },
        "Peer.add_segment": {
            "name": "add_segment",
            "location": 55,
            "return": [
                "None"
            ],
            "arguments": {
                "self": [],
                "ack": [
                    "dict"
                ]
            }
        },
        "Peer.next_ack": {
            "name": "next_ack",
            "location": 64,
            "return": [
                "Optional[dict]"
            ],
            "arguments": {
                "self": []
            }
        },
        "Receiver.__init__": {
            "name": "__init__",
            "location": 68,
            "return": [
                "None"
            ],
            "arguments": {
                "self": [],
                "running_time": [
                    "int"
                ],
                "peers": [
                    "List[Tuple[(str, int)]]"
                ],
                "window_size": [
                    "int"
                ]
            }
        },
        "Receiver.cleanup": {
            "name": "cleanup",
            "location": 82,
            "return": [
                "None"
            ],
            "arguments": {
                "self": []
            }
        },
        "Receiver.construct_ack": {
            "name": "construct_ack",
            "location": 85,
            "return": [
                "Dict[(str, Any)]"
            ],
            "arguments": {
                "self": [],
                "serialized_data": [
                    "str"
                ]
            }
        },
        "Receiver.perform_handshakes": {
            "name": "perform_handshakes",
            "location": 95,
            "return": [
                "None"
            ],
            "arguments": {
                "self": []
            }
        },
        "Receiver.run": {
            "name": "run",
            "location": 137,
            "return": [
                "NoReturn"
            ],
            "arguments": {
                "self": []
            }
        }
    },
    "network-performance-jupyter-master/src/senders.py": {
        "Sender.__init__": {
            "name": "__init__",
            "location": 17,
            "return": [
                "None"
            ],
            "arguments": {
                "self": [],
                "port": [
                    "int"
                ],
                "strategy": [
                    "src.strategies.SenderStrategy"
                ]
            }
        },
        "Sender.send": {
            "name": "send",
            "location": 29,
            "return": [
                "None"
            ],
            "arguments": {
                "self": []
            }
        },
        "Sender.recv": {
            "name": "recv",
            "location": 35,
            "return": [
                "NoReturn"
            ],
            "arguments": {
                "self": []
            }
        },
        "Sender.handshake": {
            "name": "handshake",
            "location": 40,
            "return": [
                "None"
            ],
            "arguments": {
                "self": []
            }
        },
        "Sender.run": {
            "name": "run",
            "location": 53,
            "return": [
                "None"
            ],
            "arguments": {
                "self": [],
                "seconds_to_run": [
                    "int"
                ]
            }
        }
    },
    "network-performance-jupyter-master/src/strategies.py": {
        "SenderStrategy.__init__": {
            "name": "__init__",
            "location": 6,
            "return": [
                "None"
            ],
            "arguments": {
                "self": []
            }
        },
        "SenderStrategy.next_packet_to_send": {
            "name": "next_packet_to_send",
            "location": 23,
            "return": [
                "NoReturn"
            ],
            "arguments": {
                "self": []
            }
        },
        "SenderStrategy.process_ack": {
            "name": "process_ack",
            "location": 26,
            "return": [
                "NoReturn"
            ],
            "arguments": {
                "self": [],
                "ack": [
                    "str"
                ]
            }
        },
        "FixedWindowStrategy.__init__": {
            "name": "__init__",
            "location": 31,
            "return": [
                "None"
            ],
            "arguments": {
                "self": [],
                "cwnd": [
                    "int"
                ]
            }
        },
        "FixedWindowStrategy.window_is_open": {
            "name": "window_is_open",
            "location": 36,
            "return": [
                "bool"
            ],
            "arguments": {
                "self": []
            }
        },
        "FixedWindowStrategy.next_packet_to_send": {
            "name": "next_packet_to_send",
            "location": 40,
            "return": [
                "Optional[str]"
            ],
            "arguments": {
                "self": []
            }
        },
        "FixedWindowStrategy.process_ack": {
            "name": "process_ack",
            "location": 53,
            "return": [
                "None"
            ],
            "arguments": {
                "self": [],
                "serialized_ack": [
                    "str"
                ]
            }
        },
        "CubicStrategy.__init__": {
            "name": "__init__",
            "location": 83,
            "return": [
                "None"
            ],
            "arguments": {
                "self": [],
                "c": [
                    "int"
                ]
            }
        },
        "CubicStrategy.compute_w_est": {
            "name": "compute_w_est",
            "location": 105,
            "return": [
                "int"
            ],
            "arguments": {
                "self": []
            }
        },
        "CubicStrategy.compute_w_cubic": {
            "name": "compute_w_cubic",
            "location": 115,
            "return": [
                "int"
            ],
            "arguments": {
                "self": [],
                "t": [
                    "float"
                ]
            }
        },
        "CubicStrategy.average_rtt": {
            "name": "average_rtt",
            "location": 119,
            "return": [
                "float"
            ],
            "arguments": {
                "self": []
            }
        },
        "CubicStrategy.window_is_open": {
            "name": "window_is_open",
            "location": 122,
            "return": [
                "bool"
            ],
            "arguments": {
                "self": []
            }
        },
        "CubicStrategy.next_packet_to_send": {
            "name": "next_packet_to_send",
            "location": 129,
            "return": [
                "Optional[str]"
            ],
            "arguments": {
                "self": []
            }
        },
        "CubicStrategy.process_ack": {
            "name": "process_ack",
            "location": 180,
            "return": [
                "None"
            ],
            "arguments": {
                "self": [],
                "serialized_ack": [
                    "str"
                ]
            }
        },
        "TahoeStrategy.__init__": {
            "name": "__init__",
            "location": 257,
            "return": [
                "None"
            ],
            "arguments": {
                "self": [],
                "slow_start_thresh": [
                    "int"
                ],
                "initial_cwnd": [
                    "int"
                ]
            }
        },
        "TahoeStrategy.window_is_open": {
            "name": "window_is_open",
            "location": 273,
            "return": [
                "bool"
            ],
            "arguments": {
                "self": []
            }
        },
        "TahoeStrategy.next_packet_to_send": {
            "name": "next_packet_to_send",
            "location": 280,
            "return": [
                "Optional[str]"
            ],
            "arguments": {
                "self": []
            }
        },
        "TahoeStrategy.process_ack": {
            "name": "process_ack",
            "location": 329,
            "return": [
                "None"
            ],
            "arguments": {
                "self": [],
                "serialized_ack": [
                    "str"
                ]
            }
        }
    },
    "network-performance-jupyter-master/src/__init__.py": {},
    "network-performance-jupyter-master/tests/test_receiver.py": {
        "TestPeer.test_first_segment": {
            "name": "test_first_segment",
            "location": 9,
            "return": [
                "None"
            ],
            "arguments": {
                "self": []
            }
        },
        "TestPeer.test_out_of_order_segment": {
            "name": "test_out_of_order_segment",
            "location": 21,
            "return": [
                "None"
            ],
            "arguments": {
                "self": []
            }
        },
        "TestPeer.test_recovery": {
            "name": "test_recovery",
            "location": 52,
            "return": [
                "None"
            ],
            "arguments": {
                "self": []
            }
        },
        "TestPeer.test_clears_out_window": {
            "name": "test_clears_out_window",
            "location": 93,
            "return": [
                "None"
            ],
            "arguments": {
                "self": []
            }
        }
    },
    "network-performance-jupyter-master/tests/test_strategies.py": {
        "TestTahoeStrategy.test_segments_received_in_order": {
            "name": "test_segments_received_in_order",
            "location": 8,
            "return": [
                "None"
            ],
            "arguments": {
                "self": []
            }
        },
        "TestTahoeStrategy.test_retransmitting_packets": {
            "name": "test_retransmitting_packets",
            "location": 67,
            "return": [
                "None"
            ],
            "arguments": {
                "self": []
            }
        },
        "TestTahoeStrategy.test_partial_ack": {
            "name": "test_partial_ack",
            "location": 111,
            "return": [
                "None"
            ],
            "arguments": {
                "self": []
            }
        },
        "TestRenoSender.test_segments_received_in_order": {
            "name": "test_segments_received_in_order",
            "location": 152,
            "return": [
                "None"
            ],
            "arguments": {
                "self": []
            }
        }
    },
    "network-performance-jupyter-master/tests/__init__.py": {}
}