{
    "Pattern1": {
        "points": 2,
        "pytype": {
            "not Match": 0,
            "Fail": 2
        },
        "type4py": {
            "not Match": 0,
            "Fail": 2
        },
        "hityper": {
            "not Match": 0,
            "Fail": 2
        }
    },
    "Pattern2": {
        "points": 2,
        "pytype": {
            "not Match": 0,
            "Fail": 2
        },
        "type4py": {
            "not Match": 1,
            "Fail": 1
        },
        "hityper": {
            "not Match": 1,
            "Fail": 1
        }
    },
    "Pattern3": {
        "points": 4,
        "pytype": {
            "not Match": 0,
            "Fail": 4
        },
        "type4py": {
            "not Match": 3,
            "Fail": 1
        },
        "hityper": {
            "not Match": 3,
            "Fail": 1
        }
    },
    "Pattern4": {
        "points": 4,
        "pytype": {
            "not Match": 0,
            "Fail": 4
        },
        "type4py": {
            "not Match": 3,
            "Fail": 1
        },
        "hityper": {
            "not Match": 0,
            "Fail": 4
        }
    },
    "Pattern5": {
        "points": 39,
        "pytype": {
            "not Match": 0,
            "Fail": 39
        },
        "type4py": {
            "not Match": 15,
            "Fail": 6
        },
        "hityper": {
            "not Match": 6,
            "Fail": 11
        }
    },
    "Pattern6": {
        "points": 0,
        "pytype": {
            "not Match": 0,
            "Fail": 0
        },
        "type4py": {
            "not Match": 0,
            "Fail": 0
        },
        "hityper": {
            "not Match": 0,
            "Fail": 0
        }
    }
}